README.md
setup.py
bidali/__init__.py
bidali/config.py
bidali/ensemblrestclient.py
bidali/expan.py
bidali/fegnome.py
bidali/genenames.py
bidali/pubcrawler.py
bidali/retro.py
bidali/seqanalysis.py
bidali/survivalinks.py
bidali/util.py
bidali/visualizations.py
bidali.egg-info/PKG-INFO
bidali.egg-info/SOURCES.txt
bidali.egg-info/dependency_links.txt
bidali.egg-info/not-zip-safe
bidali.egg-info/requires.txt
bidali.egg-info/top_level.txt
bidali/LSD/__init__.py
bidali/LSD/__main__.py
bidali/LSD/formats.py
bidali/LSD/dealer/__init__.py
bidali/LSD/dealer/celllines.py
bidali/LSD/dealer/cohorts.py
bidali/LSD/dealer/drugging.py
bidali/LSD/dealer/ensembl.py
bidali/LSD/dealer/entrez.py
bidali/LSD/dealer/genenames.py
bidali/LSD/dealer/sanger.py
bidali/LSD/dealer/systems.py
bidali/LSD/dealer/drugbanks/__init__.py
bidali/LSD/dealer/home/__init__.py
bidali/LSD/dealer/home/cnvdata.py
bidali/LSD/dealer/home/models.py
bidali/LSD/dealer/ontologies/__init__.py
bidali/LSD/dealer/ontologies/bioportal.py