Metadata-Version: 2.1
Name: bidali
Version: 0.1.16
Summary: Biological Data Analysis Library
Home-page: https://github.com/dicaso/bidali
Author: Christophe Van Neste
Author-email: christophe.vanneste@ugent.be
License: MIT
Platform: UNKNOWN
Requires-Python: >3.6
Provides-Extra: documentation
Provides-Extra: retro
Provides-Extra: netcdf
